dafter/__init__.py
dafter/cli.py
dafter/datasets-configs/article-influence-2015.json
dafter/datasets-configs/asu-twitter-dataset.json
dafter/datasets-configs/audio-covers.json
dafter/datasets-configs/cifar.json
dafter/datasets-configs/colleges.json
dafter/datasets-configs/crime-data-2010-present-los-angeles.json
dafter/datasets-configs/france-postal-code.json
dafter/datasets-configs/imagenet.json
dafter/datasets-configs/imdb-datasets.json
dafter/datasets-configs/imdb-most-popular.json
dafter/datasets-configs/imdb-reviews.json
dafter/datasets-configs/metmuseum-objects.json
dafter/datasets-configs/mnist.json
dafter/datasets-configs/montgomery-county-salaries.json
dafter/datasets-configs/montgomery-county-traffic-violations.json
dafter/datasets-configs/nutrient-database-usda.json
dafter/datasets-configs/plants-database-usda.json
dafter/datasets-configs/sentiment140.json
dafter/datasets-configs/significant-earthquake-database.json
dafter/datasets-configs/sst.json
dafter/datasets-configs/stl.json
dafter/datasets-configs/svhn.json
dafter/datasets-configs/trec.json
dafter/datasets-configs/twenty-newsgroups.json
dafter/fetcher/__init__.py
dafter/fetcher/constants.py
dafter/fetcher/dataset.py
dafter/fetcher/fetcher.py
dafter/fetcher/utils.py
dafter-0.2.dist-info/LICENSE
dafter-0.2.dist-info/METADATA
dafter-0.2.dist-info/WHEEL
dafter-0.2.dist-info/entry_points.txt
dafter-0.2.dist-info/top_level.txt
dafter-0.2.dist-info/RECORD
