Metadata-Version: 2.1
Name: dafter
Version: 0.2
Summary: dafter CLI
Home-page: https://github.com/vinzeebreak/dafter
Author: Vincent Houlbreque
Author-email: UNKNOWN
License: MIT
Keywords: dataset,datasets,cli,downloader
Platform: UNKNOWN
Requires-Dist: requests
Requires-Dist: tqdm
